benpipe/__init__.py
benpipe/__main__.py
benpipe/benpipe.py
benpipe/convert.py
benpipe-0.0.2.dist-info/entry_points.txt
benpipe-0.0.2.dist-info/WHEEL
benpipe-0.0.2.dist-info/METADATA
benpipe-0.0.2.dist-info/RECORD
